mihifepe/__init__.py
mihifepe/__main__.py
mihifepe/compute_p_values.py
mihifepe/constants.py
mihifepe/feature.py
mihifepe/interactions.py
mihifepe/master.py
mihifepe/pipelines.py
mihifepe/utils.py
mihifepe/worker.py
mihifepe/fdr/__init__.py
mihifepe/fdr/__main__.py
mihifepe/fdr/fdr_algorithms.py
mihifepe/fdr/hierarchical_fdr_control.py
mihifepe/simulation/__init__.py
mihifepe/simulation/__main__.py
mihifepe/simulation/gen_model_template.py
mihifepe/simulation/model.py
mihifepe/simulation/run_simulations.py
mihifepe/simulation/run_trials.py
mihifepe/simulation/simulation.py
tests/__init__.py
tests/gen_condor_tests.py
tests/test_mihifepe.py
tests/condor_tests/test_mihifepe.py
tests/condor_tests/test_mihifepe/test_condor_simulation_all_pairwise_interactions_fdr.json
tests/condor_tests/test_mihifepe/test_condor_simulation_all_pairwise_interactions_pvalues.csv
tests/condor_tests/test_mihifepe/test_condor_simulation_clustering_hierarchy_fdr.json
tests/condor_tests/test_mihifepe/test_condor_simulation_clustering_hierarchy_pvalues.csv
tests/condor_tests/test_mihifepe/test_condor_simulation_gaussian_noise_fdr.json
tests/condor_tests/test_mihifepe/test_condor_simulation_gaussian_noise_pvalues.csv
tests/condor_tests/test_mihifepe/test_condor_simulation_interactions_fdr.json
tests/condor_tests/test_mihifepe/test_condor_simulation_interactions_pvalues.csv
tests/condor_tests/test_mihifepe/test_condor_simulation_noisy_interactions_fdr.json
tests/condor_tests/test_mihifepe/test_condor_simulation_noisy_interactions_pvalues.csv
tests/condor_tests/test_mihifepe/test_condor_simulation_random_hierarchy_fdr.json
tests/condor_tests/test_mihifepe/test_condor_simulation_random_hierarchy_pvalues.csv
tests/condor_tests/test_mihifepe/test_condor_simulation_shuffling_interactions_fdr.json
tests/condor_tests/test_mihifepe/test_condor_simulation_shuffling_interactions_pvalues.csv
tests/condor_tests/test_mihifepe/test_condor_simulation_shuffling_perturbation_fdr.json
mihifepe-0.2.2.dist-info/AUTHORS.rst
mihifepe-0.2.2.dist-info/LICENSE
mihifepe-0.2.2.dist-info/METADATA
mihifepe-0.2.2.dist-info/WHEEL
mihifepe-0.2.2.dist-info/entry_points.txt
mihifepe-0.2.2.dist-info/top_level.txt
mihifepe-0.2.2.dist-info/zip-safe
mihifepe-0.2.2.dist-info/RECORD
