Metadata-Version: 2.1
Name: mihifepe
Version: 0.2.2
Summary: Model Interpretability via Hierarchical Feature Perturbation
Home-page: https://github.com/Craven-Biostat-Lab/mihifepe
Author: Akshay Sood
Author-email: sood.iitd@gmail.com
License: MIT
Keywords: mihifepe
Platform: UNKNOWN
Classifier: Development Status :: 2 - Pre-Alpha
Classifier: Environment :: Console
Classifier: Intended Audience :: Science/Research
Classifier: License :: OSI Approved :: MIT License
Classifier: Programming Language :: Python :: 3.5
Classifier: Programming Language :: Python :: 3.6
Classifier: Programming Language :: Python :: 3.7
Classifier: Programming Language :: Python :: Implementation :: CPython
Classifier: Topic :: Scientific/Engineering :: Artificial Intelligence
Requires-Python: >= 3.5
Requires-Dist: anytree
Requires-Dist: cityhash
Requires-Dist: h5py
Requires-Dist: numpy
Requires-Dist: pyhashxx
Requires-Dist: scikit-learn
Requires-Dist: scipy
Requires-Dist: sympy
